<?xml version="1.0" encoding="UTF-8"?>
<TEMPLATE comment="" filename="category" hidden="1" id="7033940360480325058" templateid="746228487600132129" type="page">
	<ALLOWED enabled="stage" templateid="-2776294439780559659"/>
	<ALLOWED enabled="stage" templateid="-7623187676376246123"/>
	<ALLOWED enabled="sup_content,sub_content" templateid="-1889781886281073692"/>
	<ALLOWED enabled="sup_content,sub_content" templateid="-8969919162802954099"/>
	<ALLOWED enabled="sup_content,sub_content" templateid="3857720796743261453"/>
	<EXTENSION file="html" link="json" replaceable="false" templateSet="9062318847741885912"/>
	<LANG displayname="Category" language="EN"/>
	<LANG displayname="Kategorie" language="DE"/>
	<TEMPLATEBODY name="stage">
		<LANG language="DE"/>
		<LANG language="EN"/>
	</TEMPLATEBODY>
	<TEMPLATEBODY name="sup_content">
		<LANG language="DE"/>
		<LANG language="EN"/>
	</TEMPLATEBODY>
	<TEMPLATEBODY name="sub_content">
		<LANG language="DE"/>
		<LANG language="EN"/>
	</TEMPLATEBODY>
</TEMPLATE>
